ducktools/env/__init__.py
ducktools/env/__main__.py
ducktools/env/_lazy_imports.py
ducktools/env/_logger.py
ducktools/env/_run.py
ducktools/env/_sqlclasses.py
ducktools/env/_version.py
ducktools/env/bundle.py
ducktools/env/bundled_data.py
ducktools/env/catalogue.py
ducktools/env/config.py
ducktools/env/environment_specs.py
ducktools/env/exceptions.py
ducktools/env/manager.py
ducktools/env/platform_paths.py
ducktools/env/register.py
ducktools/env/bootstrapping/bootstrap.py
ducktools/env/bootstrapping/bundle_main.py
ducktools/env/bootstrapping/version_check.py
ducktools/env/bootstrapping/zipapp_main.py
ducktools/env/bootstrapping/zipapp_main_dtrun.py
ducktools/env/scripts/__init__.py
ducktools/env/scripts/create_zipapp.py
ducktools/env/scripts/get_pip.py
ducktools/env/scripts/get_uv.py
ducktools_env-0.4.4.dist-info/licenses/LICENSE
ducktools_env-0.4.4.dist-info/METADATA
ducktools_env-0.4.4.dist-info/WHEEL
ducktools_env-0.4.4.dist-info/entry_points.txt
ducktools_env-0.4.4.dist-info/top_level.txt
ducktools_env-0.4.4.dist-info/RECORD
