Metadata-Version: 2.4
Name: ducktools-env
Version: 0.4.4
Summary: Virtual environment management tools and application bundle builder
Author: David C Ellis
Classifier: Development Status :: 2 - Pre-Alpha
Classifier: Programming Language :: Python :: 3.10
Classifier: Programming Language :: Python :: 3.11
Classifier: Programming Language :: Python :: 3.12
Classifier: Programming Language :: Python :: 3.13
Classifier: Programming Language :: Python :: 3.14
Classifier: License :: OSI Approved :: MIT License
Classifier: Operating System :: Microsoft :: Windows
Classifier: Operating System :: POSIX :: Linux
Requires-Python: >=3.10
License-File: LICENSE
Requires-Dist: ducktools-classbuilder>=0.12.3
Requires-Dist: ducktools-lazyimporter>=0.7.0
Requires-Dist: ducktools-scriptmetadata>=0.2.0
Requires-Dist: ducktools-pythonfinder>=0.8.1
Requires-Dist: tomli>=2.2; python_version < "3.11"
Requires-Dist: packaging>=24.2
Dynamic: license-file
